automata_practical_exam/__init__.py
automata_practical_exam/DFA_task/__init__.py
automata_practical_exam/DFA_task/dfa.py
automata_practical_exam/Turing_Machine/Turing_Machine.py
automata_practical_exam/Turing_Machine/__init__.py
tests/__init__.py
tests/unit_test_dfa.py
tests/unit_test_turing.py
automata_practical_exam-0.1.2.dist-info/METADATA
automata_practical_exam-0.1.2.dist-info/WHEEL
automata_practical_exam-0.1.2.dist-info/top_level.txt
automata_practical_exam-0.1.2.dist-info/RECORD
