Metadata-Version: 2.4
Name: automata_practical_exam
Version: 0.1.2
Summary: A description of your package
Home-page: https://github.com/Moham6dFathy/automata_practical_exam_4552
Author: Mohamed Fathy
Author-email: moham6dfathy@gmail.com
Classifier: Programming Language :: Python :: 3
Classifier: License :: OSI Approved :: MIT License
Classifier: Operating System :: OS Independent
Requires-Dist: pytest
Dynamic: author
Dynamic: author-email
Dynamic: classifier
Dynamic: description
Dynamic: description-content-type
Dynamic: home-page
Dynamic: requires-dist
Dynamic: summary
